[
  {
    "event": "catalogue",
    "data": {
      "section": "overview",
      "content": {
        "territoryToday": {
          "markdown": "# Italy Today\n\nItaly is a country in Europe. It is the fifth largest country in Europe by area and the third most populous country in Europe. Italy is a member of the European Union and the Eurozone."
        },
        "territoryHistory": {
          "markdown": "# Italy History\n\nItaly has a long and rich history. It is the birthplace of the Roman Empire and the Renaissance. Italy is a member of the European Union and the Eurozone."
        },
        "localityToday": {
          "markdown": "# Rome Today\n\nRome is the capital of Italy. It is a city of history and culture. Rome is a member of the European Union and the Eurozone."
        },
        "localityHistory": {
          "markdown": "# Rome History\n\nRome has a long and rich history. It is the birthplace of the Roman Empire and the Renaissance. Rome is a member of the European Union and the Eurozone."
        },
        "neighborhoodToday": {
          "markdown": "# Rome Neighborhood\n\nRome is the capital of Italy. It is a city of history and culture."
        },
        "neighborhoodHistory": {
          "markdown": "# Rome Neighborhood History\n\nRome has a long and rich history. It is the birthplace of the Roman Empire and the Renaissance."
        }
      }
    }
  },
  {
    "event": "catalogue",
    "data": {
      "section": "cuisine",
      "config": {
        "textOverlayImage": true,
        "card": {
          "type": "dishCard"
        },
        "columns": 2
      },
      "content": {
        "regionalCuisine": {
          "markdown": "A taste of regional dishes from the area.",
          "cards": [
            {
              "local_name": "Shakshuka",
              "global_name": "Shakshuka",
              "description": "Shakshuka is a dish of eggs cooked in a sauce of tomatoes, onions, and garlic.",
              "image_url": "https://i2.wp.com/www.downshiftology.com/wp-content/uploads/2023/12/Shakshuka-main-1.jpg"
            },
            {
              "local_name": "Moussaka",
              "global_name": "Moussaka",
              "description": "Moussaka is a dish of eggplant, potatoes, and ground beef.",
              "image_url": "https://www.giallozafferano.com/images/302-30219/moussaka_1200x800.jpg"
            }
          ]
        }
      }
    }
  },
  {
    "event": "catalogue",
    "data": {
      "section": "architecture",
      "content": {
        "heritage": {
          "markdown": "introductory text about the heritage sites and historical significance",
          "cards": [
            {
              "type": "Feature",
              "geometry": {
                "type": "Point",
                "coordinates": [12.4964, 41.9028]
              },
              "properties": {
                "title": "Colosseum",
                "description": "Ancient Roman amphitheater"
              }
            },
            {
              "type": "Feature",
              "geometry": {
                "type": "Point",
                "coordinates": [12.4833, 41.9]
              },
              "properties": {
                "title": "Roman Forum",
                "description": "Ancient Roman public square",
                "category": "landmark",
                "img_url": "https://lh3.googleusercontent.com/gps-cs-s/AHVAweot9IkdyGNQvGJfdjn8OEYsc3ZOlZUX-PRm9wPnUSi2EoKuTH4uUngwlVk4XBx4ho99BNV_9fIQ48xVXAgCLVFbxJdcEZqmXGrmOaZL5sEk6AcC9nGKsftOcHbQEN0TK_l-EoBa=s680-w680-h510-rw"
              }
            }
          ]
        }
      }
    }
  }
]
